mkdocs_suppress_logs_plugin/__init__.py
mkdocs_suppress_logs_plugin-0.1.1.dist-info/licenses/LICENSE
mkdocs_suppress_logs_plugin-0.1.1.dist-info/METADATA
mkdocs_suppress_logs_plugin-0.1.1.dist-info/WHEEL
mkdocs_suppress_logs_plugin-0.1.1.dist-info/entry_points.txt
mkdocs_suppress_logs_plugin-0.1.1.dist-info/top_level.txt
mkdocs_suppress_logs_plugin-0.1.1.dist-info/RECORD
