Metadata-Version: 2.4
Name: mkdocs-suppress-logs-plugin
Version: 0.1.1
Summary: MkDocs plugin to suppress unwanted log messages using pattern matching.
Home-page: https://github.com/darrelk/mkdocs-suppress-logs-plugin
Author: darrelk
Author-email: darrelkley@gmail.com
License: MIT
Requires-Python: >=3.7
License-File: LICENSE
Requires-Dist: mkdocs>=1.1
Dynamic: author
Dynamic: author-email
Dynamic: description
Dynamic: description-content-type
Dynamic: home-page
Dynamic: license
Dynamic: license-file
Dynamic: requires-dist
Dynamic: requires-python
Dynamic: summary
